{"cameraMode":{"drawMode":0,"name":"Shaded","section":"Shading Mode"},"sceneLighting":true,"audioPlay":false,"sceneViewState":{"m_AlwaysRefresh":false,"showFog":true,"showSkybox":true,"showFlares":true,"showImageEffects":true,"showParticleSystems":true,"showVisualEffectGraphs":true,"m_FxEnabled":true},"in2DMode":false,"pivot":{"x":406.2964172363281,"y":256.0133361816406,"z":0.3795814514160156},"rotation":{"x":-0.09263219684362412,"y":0.8971052169799805,"z":-0.22554537653923036,"w":-0.36844396591186526},"size":27.239810943603517,"orthographic":false}